choice_evylah/__init__.py
choice_evylah/choice_evylah.py
choice_evylah-0.0.1.dist-info/METADATA
choice_evylah-0.0.1.dist-info/WHEEL
choice_evylah-0.0.1.dist-info/licenses/LICENSE
choice_evylah-0.0.1.dist-info/RECORD
